data_memory.v
module data_memory (
    input wire clk,
    input wire mem_read,
    input wire mem_write,
    input wire [31:0] address,
    input wire [31:0] write_data,
    output wire [31:0] read_data
);

    // Memory array (1KB for simplicity)
    reg [31:0] memory [0:255];
    integer i;
    
    // Initialize memory to 0
    initial begin
        for (i = 0; i < 256; i = i + 1)
            memory[i] = 32'h0;
    end
    
    // Write operation (synchronous)
    always @(posedge clk) begin
        if (mem_write)
            memory[address[9:2]] <= write_data;
    end
    
    // Read operation (asynchronous)
    assign read_data = mem_read ? memory[address[9:2]] : 32'h0;

endmodule

src/core/alu.v
module alu (
    input wire [31:0] a,
    input wire [31:0] b,
    input wire [3:0] alu_control,
    output reg [31:0] result,
    output wire zero,
    // Add branch-specific outputs
    output reg branch_result
);

    // ALU control codes
    parameter ALU_ADD = 4'b0000;
    parameter ALU_SUB = 4'b0001;
    parameter ALU_AND = 4'b0010;
    parameter ALU_OR  = 4'b0011;
    parameter ALU_XOR = 4'b0100;
    parameter ALU_SLL = 4'b0101; // Shift left logical
    parameter ALU_SRL = 4'b0110; // Shift right logical
    parameter ALU_SRA = 4'b0111; // Shift right arithmetic
    parameter ALU_SLT = 4'b1000; // Set less than (signed)
    parameter ALU_SLTU = 4'b1001; // Set less than unsigned
    // Branch operation codes
    parameter ALU_BEQ = 4'b1010; // Branch equal
    parameter ALU_BNE = 4'b1011; // Branch not equal
    parameter ALU_BLT = 4'b1100; // Branch less than
    parameter ALU_BGE = 4'b1101; // Branch greater than or equal
    parameter ALU_BLTU = 4'b1110; // Branch less than unsigned
    parameter ALU_BGEU = 4'b1111; // Branch greater than or equal unsigned
    
    // ALU operation
    always @(*) begin
        case (alu_control)
            ALU_ADD: result = a + b;
            ALU_SUB: result = a - b;
            ALU_AND: result = a & b;
            ALU_OR:  result = a | b;
            ALU_XOR: result = a ^ b;
            ALU_SLL: result = a << b[4:0];
            ALU_SRL: result = a >> b[4:0];
            ALU_SRA: result = $signed(a) >>> b[4:0];
            ALU_SLT: result = ($signed(a) < $signed(b)) ? 32'h1 : 32'h0;
            ALU_SLTU: result = (a < b) ? 32'h1 : 32'h0;
            // Branch operations compute the same result as SUB
            ALU_BEQ, ALU_BNE, ALU_BLT, ALU_BGE, ALU_BLTU, ALU_BGEU: result = a - b;
            default: result = 32'h0;
        endcase
    end
    
    // Zero flag
    assign zero = (result == 32'h0);

    // Branch evaluation result
    always @(*) begin
        case (alu_control)
            ALU_BEQ:  branch_result = (a == b);
            ALU_BNE:  branch_result = (a != b);
            ALU_BLT:  branch_result = ($signed(a) < $signed(b));
            ALU_BGE:  branch_result = ($signed(a) >= $signed(b));
            ALU_BLTU: branch_result = (a < b);
            ALU_BGEU: branch_result = (a >= b);
            default:  branch_result = 1'b0;
        endcase
    end

endmodule

immediate_generator.v
module immediate_generator (
    input wire [31:0] instruction,
    output reg [31:0] imm_extended
);

    wire [6:0] opcode = instruction[6:0];
    
    always @(*) begin
        case(opcode)
            7'b0010011, // I-type ALU operations
            7'b0000011: // I-type loads
                imm_extended = {{20{instruction[31]}}, instruction[31:20]};
                
            7'b0100011: // S-type
                imm_extended = {{20{instruction[31]}}, instruction[31:25], instruction[11:7]};
                
            7'b1100011: // B-type
                imm_extended = {{20{instruction[31]}}, instruction[7], instruction[30:25], instruction[11:8], 1'b0};
                
            7'b0110111, // U-type LUI
            7'b0010111: // U-type AUIPC
                imm_extended = {instruction[31:12], 12'h000};
                
            7'b1101111: // J-type JAL
                imm_extended = {{12{instruction[31]}}, instruction[19:12], instruction[20], instruction[30:21], 1'b0};
                
            default:
                imm_extended = 32'h0;
        endcase
    end

endmodule

register_file.v
module register_file (
    input wire clk,
    input wire rst_n,
    input wire reg_write,
    input wire [4:0] read_reg1,
    input wire [4:0] read_reg2,
    input wire [4:0] write_reg,
    input wire [31:0] write_data,
    output wire [31:0] read_data1,
    output wire [31:0] read_data2
);

    // 32 registers, each 32-bit wide
    reg [31:0] registers [0:31];
    integer i;
    
    // Initialize all registers to 0
    initial begin
        for (i = 0; i < 32; i = i + 1)
            registers[i] = 32'h0;
    end
    
    // Write operation (at positive clock edge)
    always @(posedge clk) begin
        if (reg_write && write_reg != 0) // Register x0 must always be 0
            registers[write_reg] <= write_data;
    end
    
    // Read operations (combinational)
    assign read_data1 = (read_reg1 == 0) ? 32'h0 : registers[read_reg1];
    assign read_data2 = (read_reg2 == 0) ? 32'h0 : registers[read_reg2];

endmodule

control_unit.v
module control_unit (
    input wire [6:0] opcode,
    input wire [2:0] funct3,
    input wire [6:0] funct7,
    output reg reg_write,
    output reg mem_read,
    output reg mem_write,
    output reg branch,
    output reg mem_to_reg,
    output reg alu_src,
    output reg [1:0] alu_op,
    output reg [3:0] alu_control
);

    // RISC-V opcode definitions
    parameter R_TYPE     = 7'b0110011;
    parameter I_TYPE_ALU = 7'b0010011;
    parameter I_TYPE_LOAD = 7'b0000011;
    parameter S_TYPE     = 7'b0100011;
    parameter B_TYPE     = 7'b1100011;
    parameter U_TYPE_LUI = 7'b0110111;
    parameter U_TYPE_AUIPC = 7'b0010111;
    parameter J_TYPE_JAL = 7'b1101111;
    parameter I_TYPE_JALR = 7'b1100111;
    
    // Main control signals
    always @(*) begin
        case(opcode)
            R_TYPE: begin
                reg_write = 1'b1;
                mem_read = 1'b0;
                mem_write = 1'b0;
                branch = 1'b0;
                mem_to_reg = 1'b0;
                alu_src = 1'b0;
                alu_op = 2'b10;
            end
            I_TYPE_ALU: begin
                reg_write = 1'b1;
                mem_read = 1'b0;
                mem_write = 1'b0;
                branch = 1'b0;
                mem_to_reg = 1'b0;
                alu_src = 1'b1;
                alu_op = 2'b10;
            end
            I_TYPE_LOAD: begin
                reg_write = 1'b1;
                mem_read = 1'b1;
                mem_write = 1'b0;
                branch = 1'b0;
                mem_to_reg = 1'b1;
                alu_src = 1'b1;
                alu_op = 2'b00;
            end
            S_TYPE: begin
                reg_write = 1'b0;
                mem_read = 1'b0;
                mem_write = 1'b1;
                branch = 1'b0;
                mem_to_reg = 1'bx; // Don't care
                alu_src = 1'b1;
                alu_op = 2'b00;
            end
            B_TYPE: begin
                reg_write = 1'b0;
                mem_read = 1'b0;
                mem_write = 1'b0;
                branch = 1'b1;
                mem_to_reg = 1'bx; // Don't care
                alu_src = 1'b0;
                alu_op = 2'b01;
            end
            default: begin
                reg_write = 1'b0;
                mem_read = 1'b0;
                mem_write = 1'b0;
                branch = 1'b0;
                mem_to_reg = 1'b0;
                alu_src = 1'b0;
                alu_op = 2'b00;
            end
        endcase
    end

    // ALU control logic
    always @(*) begin
        case(alu_op)
            2'b00: alu_control = 4'b0000; // ADD for loads/stores
            2'b01: alu_control = 4'b0001; // SUB for branches
            2'b10: begin // R-type or I-type ALU
                case(funct3)
                    3'b000: begin
                        // ADD or SUB (for R-type)
                        if (opcode == R_TYPE && funct7 == 7'b0100000)
                            alu_control = 4'b0001; // SUB
                        else
                            alu_control = 4'b0000; // ADD
                    end
                    3'b001: alu_control = 4'b0101; // SLL
                    3'b010: alu_control = 4'b1000; // SLT
                    3'b011: alu_control = 4'b1001; // SLTU
                    3'b100: alu_control = 4'b0100; // XOR
                    3'b101: begin
                        if (funct7 == 7'b0100000)
                            alu_control = 4'b0111; // SRA
                        else
                            alu_control = 4'b0110; // SRL
                    end
                    3'b110: alu_control = 4'b0011; // OR
                    3'b111: alu_control = 4'b0010; // AND
                    default: alu_control = 4'b0000;
                endcase
            end
            default: alu_control = 4'b0000;
        endcase
    end

endmodule

src/memory/instruction_memory.v
module instruction_memory (
    input wire [31:0] pc,
    output wire [31:0] instruction
);

    // For a simple implementation, we'll use a small ROM
    reg [31:0] memory [0:255]; // 256 words of memory
    integer i, file_handle;
    
    // Initialize from file if provided, otherwise use default program
    initial begin
        // Default: Initialize all memory to 0
        for (i = 0; i < 256; i = i + 1)
            memory[i] = 32'h0;
            
        // Try to load the program
        $display("Loading program from test.hex");
        file_handle = $fopen("test.hex", "r");
        if (file_handle == 0) begin
            $display("ERROR: Could not open test.hex");
        end else begin
            $fclose(file_handle);
            $readmemh("test.hex", memory);
            $display("Program loaded successfully");
        end
        
        // Debug: Display the first few instructions
        $display("First 8 instructions:");
        for (i = 0; i < 8; i = i + 1)
            $display("memory[%0d] = 0x%h", i, memory[i]);
    end
    
    // Word-aligned access (address ignores lower 2 bits)
    assign instruction = memory[pc[9:2]]; // PC is byte-addressed, but memory is word-addressed

endmodule

program_counter.v
module program_counter (
    input wire clk,
    input wire rst_n,
    input wire [31:0] pc_next,
    output reg [31:0] pc_current
);

    always @(posedge clk or negedge rst_n) begin
        if (!rst_n)
            pc_current <= 32'h0;
        else
            pc_current <= pc_next;
    end

endmodule

src/core/riscv_cpu.v
module riscv_cpu (
    input wire clk,
    input wire rst_n,
    output wire [31:0] pc_out
);
    // Wires for connecting components
    wire [31:0] pc_current;
    wire [31:0] pc_next;
    wire [31:0] instruction;
    wire [31:0] alu_result;
    wire [31:0] read_data1, read_data2;
    wire [31:0] imm_extended;
    wire [31:0] write_data;
    wire [31:0] read_data_mem;
    wire [4:0] rd, rs1, rs2;
    wire [2:0] funct3;
    wire [6:0] funct7;
    wire [6:0] opcode;
    
    // Control signals
    wire reg_write;
    wire mem_read;
    wire mem_write;
    wire branch;
    wire mem_to_reg;
    wire alu_src;
    wire [1:0] alu_op;
    wire [3:0] alu_control;
    wire zero_flag;
    wire branch_result;    // New wire for branch condition result
    wire pc_src;
    
    // Program Counter
    program_counter pc (
        .clk(clk),
        .rst_n(rst_n),
        .pc_next(pc_next),
        .pc_current(pc_current)
    );
    
    // Instruction Memory
    instruction_memory imem (
        .pc(pc_current),
        .instruction(instruction)
    );
    
    // Instruction decoding
    assign opcode = instruction[6:0];
    assign rd = instruction[11:7];
    assign funct3 = instruction[14:12];
    assign rs1 = instruction[19:15];
    assign rs2 = instruction[24:20];
    assign funct7 = instruction[31:25];
    
    // Control Unit
    control_unit cu (
        .opcode(opcode),
        .funct3(funct3),
        .funct7(funct7),
        .reg_write(reg_write),
        .mem_read(mem_read),
        .mem_write(mem_write),
        .branch(branch),
        .mem_to_reg(mem_to_reg),
        .alu_src(alu_src),
        .alu_op(alu_op),
        .alu_control(alu_control)
    );
    
    // Register File
    register_file rf (
        .clk(clk),
        .rst_n(rst_n),
        .reg_write(reg_write),
        .read_reg1(rs1),
        .read_reg2(rs2),
        .write_reg(rd),
        .write_data(write_data),
        .read_data1(read_data1),
        .read_data2(read_data2)
    );
    
    // Immediate Generator
    immediate_generator immgen (
        .instruction(instruction),
        .imm_extended(imm_extended)
    );
    
    // ALU source mux
    wire [31:0] alu_input2 = alu_src ? imm_extended : read_data2;
    
    // ALU
    alu main_alu (
        .a(read_data1),
        .b(alu_input2),
        .alu_control(alu_control),
        .result(alu_result),
        .zero(zero_flag),
        .branch_result(branch_result)    // Connect the branch_result output
    );
    
    // Data Memory
    data_memory dmem (
        .clk(clk),
        .mem_read(mem_read),
        .mem_write(mem_write),
        .address(alu_result),
        .write_data(read_data2),
        .read_data(read_data_mem)
    );
    
    // Write back mux
    assign write_data = mem_to_reg ? read_data_mem : alu_result;
    
    // Branch logic - use branch_result instead of zero_flag
    assign pc_src = branch & branch_result;
    assign pc_next = pc_src ? (pc_current + imm_extended) : (pc_current + 4);
    
    // Output
    assign pc_out = pc_current;
    
endmodule

src/testbench/tb_riscv_cpu.v
module tb_riscv_cpu;
    reg clk;
    reg rst_n;
    wire [31:0] pc_out;
    integer i;
    
    // Instantiate the RISC-V CPU
    riscv_cpu dut (
        .clk(clk),
        .rst_n(rst_n),
        .pc_out(pc_out)
    );
    
    // Clock generation
    initial begin
        clk = 0;
        forever #5 clk = ~clk;
    end
    
    // Waveform dumping
    initial begin
        $dumpfile("waveform.vcd");
        $dumpvars(0, tb_riscv_cpu);
    end
    
    // Test sequence
    initial begin
        $display("Starting RISC-V CPU test...");
        
        // Reset the CPU
        rst_n = 0;
        #10;
        rst_n = 1;
        
        // Run longer to allow all instructions to execute
        #1500;  // Increased from 1000 to 1500
        
        // Print register file contents at end
        $display("\nFinal Register File Contents:");
        for (i = 0; i < 10; i = i + 1) begin
            $display("x%0d = %0d (0x%h)", i, dut.rf.registers[i], dut.rf.registers[i]);
        end
        
        // Print Fibonacci sequence from memory
        $display("\nFibonacci Sequence in Memory:");
        for (i = 0; i < 8; i = i + 1) begin
            $display("mem[%0d] = %0d (0x%h)", i, dut.dmem.memory[i], dut.dmem.memory[i]);
        end
        
        // End simulation
        $display("\nEnd of test. PC = %h", pc_out);
        $finish;
    end
    
endmodule

waveform.vcd
$date
	Mon Apr 14 18:48:59 2025
$end
$version
	Icarus Verilog
$end
$timescale
	1s
$end
$scope module tb_riscv_cpu $end
$var wire 32 ! pc_out [31:0] $end
$var reg 1 " clk $end
$var reg 1 # rst_n $end
$var integer 32 $ i [31:0] $end
$scope module dut $end
$var wire 1 " clk $end
$var wire 32 % pc_out [31:0] $end
$var wire 1 & pc_src $end
$var wire 1 # rst_n $end
$var wire 1 ' zero_flag $end
$var wire 32 ( write_data [31:0] $end
$var wire 5 ) rs2 [4:0] $end
$var wire 5 * rs1 [4:0] $end
$var wire 1 + reg_write $end
$var wire 32 , read_data_mem [31:0] $end
$var wire 32 - read_data2 [31:0] $end
$var wire 32 . read_data1 [31:0] $end
$var wire 5 / rd [4:0] $end
$var wire 32 0 pc_next [31:0] $end
$var wire 32 1 pc_current [31:0] $end
$var wire 7 2 opcode [6:0] $end
$var wire 1 3 mem_write $end
$var wire 1 4 mem_to_reg $end
$var wire 1 5 mem_read $end
$var wire 32 6 instruction [31:0] $end
$var wire 32 7 imm_extended [31:0] $end
$var wire 7 8 funct7 [6:0] $end
$var wire 3 9 funct3 [2:0] $end
$var wire 1 : branch_result $end
$var wire 1 ; branch $end
$var wire 1 < alu_src $end
$var wire 32 = alu_result [31:0] $end
$var wire 2 > alu_op [1:0] $end
$var wire 32 ? alu_input2 [31:0] $end
$var wire 4 @ alu_control [3:0] $end
$scope module cu $end
$var wire 3 A funct3 [2:0] $end
$var wire 7 B funct7 [6:0] $end
$var wire 7 C opcode [6:0] $end
$var parameter 7 D B_TYPE $end
$var parameter 7 E I_TYPE_ALU $end
$var parameter 7 F I_TYPE_JALR $end
$var parameter 7 G I_TYPE_LOAD $end
$var parameter 7 H J_TYPE_JAL $end
$var parameter 7 I R_TYPE $end
$var parameter 7 J S_TYPE $end
$var parameter 7 K U_TYPE_AUIPC $end
$var parameter 7 L U_TYPE_LUI $end
$var reg 4 M alu_control [3:0] $end
$var reg 2 N alu_op [1:0] $end
$var reg 1 < alu_src $end
$var reg 1 ; branch $end
$var reg 1 5 mem_read $end
$var reg 1 4 mem_to_reg $end
$var reg 1 3 mem_write $end
$var reg 1 + reg_write $end
$upscope $end
$scope module dmem $end
$var wire 1 " clk $end
$var wire 1 5 mem_read $end
$var wire 1 3 mem_write $end
$var wire 32 O write_data [31:0] $end
$var wire 32 P read_data [31:0] $end
$var wire 32 Q address [31:0] $end
$var integer 32 R i [31:0] $end
$upscope $end
$scope module imem $end
$var wire 32 S instruction [31:0] $end
$var wire 32 T pc [31:0] $end
$var integer 32 U file_handle [31:0] $end
$var integer 32 V i [31:0] $end
$upscope $end
$scope module immgen $end
$var wire 32 W instruction [31:0] $end
$var wire 7 X opcode [6:0] $end
$var reg 32 Y imm_extended [31:0] $end
$upscope $end
$scope module main_alu $end
$var wire 4 Z alu_control [3:0] $end
$var wire 32 [ b [31:0] $end
$var wire 1 ' zero $end
$var wire 32 \ a [31:0] $end
$var parameter 4 ] ALU_ADD $end
$var parameter 4 ^ ALU_AND $end
$var parameter 4 _ ALU_BEQ $end
$var parameter 4 ` ALU_BGE $end
$var parameter 4 a ALU_BGEU $end
$var parameter 4 b ALU_BLT $end
$var parameter 4 c ALU_BLTU $end
$var parameter 4 d ALU_BNE $end
$var parameter 4 e ALU_OR $end
$var parameter 4 f ALU_SLL $end
$var parameter 4 g ALU_SLT $end
$var parameter 4 h ALU_SLTU $end
$var parameter 4 i ALU_SRA $end
$var parameter 4 j ALU_SRL $end
$var parameter 4 k ALU_SUB $end
$var parameter 4 l ALU_XOR $end
$var reg 1 : branch_result $end
$var reg 32 m result [31:0] $end
$upscope $end
$scope module pc $end
$var wire 1 " clk $end
$var wire 32 n pc_next [31:0] $end
$var wire 1 # rst_n $end
$var reg 32 o pc_current [31:0] $end
$upscope $end
$scope module rf $end
$var wire 1 " clk $end
$var wire 5 p read_reg1 [4:0] $end
$var wire 5 q read_reg2 [4:0] $end
$var wire 1 + reg_write $end
$var wire 1 # rst_n $end
$var wire 32 r write_data [31:0] $end
$var wire 5 s write_reg [4:0] $end
$var wire 32 t read_data2 [31:0] $end
$var wire 32 u read_data1 [31:0] $end
$var integer 32 v i [31:0] $end
$upscope $end
$upscope $end
$upscope $end
$enddefinitions $end
$comment Show the parameter values. $end
$dumpall
b100 l
b1 k
b110 j
b111 i
b1001 h
b1000 g
b101 f
b11 e
b1011 d
b1110 c
b1100 b
b1111 a
b1101 `
b1010 _
b10 ^
b0 ]
b110111 L
b10111 K
b100011 J
b110011 I
b1101111 H
b11 G
b1100111 F
b10011 E
b1100011 D
$end
#0
$dumpvars
b100000 v
b0 u
b0 t
b1 s
b1010 r
b1010 q
b0 p
b0 o
b100 n
b1010 m
b0 \
b1010 [
b0 Z
b1010 Y
b10011 X
b101000000000000010010011 W
b1000 V
b10000000000000000000000000000011 U
b0 T
b101000000000000010010011 S
b100000000 R
b1010 Q
b0 P
b0 O
b10 N
b0 M
b10011 C
b0 B
b0 A
b0 @
b1010 ?
b10 >
b1010 =
1<
0;
0:
b0 9
b0 8
b1010 7
b101000000000000010010011 6
05
04
03
b10011 2
b0 1
b100 0
b1 /
b0 .
b0 -
b0 ,
1+
b0 *
b1010 )
b1010 (
0'
0&
b0 %
bx $
0#
0"
b0 !
$end
#5
1"
#10
0"
1#
#15
b10 /
b10 s
b101000000000000100010011 6
b101000000000000100010011 S
b101000000000000100010011 W
b1000 0
b1000 n
b100 !
b100 %
b100 1
b100 T
b100 o
1"
#20
0"
#25
b10100 (
b10100 r
b10100 =
b10100 Q
b10100 m
b10100 ?
b10100 [
b10100 7
b10100 Y
b10100 )
b10100 q
b11 /
b11 s
b1010000000000000110010011 6
b1010000000000000110010011 S
b1010000000000000110010011 W
b1100 0
b1100 n
b1000 !
b1000 %
b1000 1
b1000 T
b1000 o
1"
#30
0"
#35
b0 (
b0 r
1'
b0 =
b0 Q
b0 m
b0 ?
b0 [
b0 7
b0 Y
b0 )
b0 q
b110 /
b110 s
b1100010011 6
b1100010011 S
b1100010011 W
b10000 0
b10000 n
b1100 !
b1100 %
b1100 1
b1100 T
b1100 o
1"
#40
0"
#45
1&
1:
b1010 ?
b1010 [
b1010 -
b1010 O
b1010 t
b1010 .
b1010 \
b1010 u
b1010 @
b1010 M
b1010 Z
b1 >
b1 N
0<
x4
1;
0+
b1000 7
b1000 Y
b1100011 X
b1 )
b1 q
b10 *
b10 p
b1000 /
b1000 s
b1100011 2
b1100011 C
b100010000010001100011 6
b100010000010001100011 S
b100010000010001100011 W
b11000 0
b11000 n
b10000 !
b10000 %
b10000 1
b10000 T
b10000 o
1"
#50
0"
#55
b0 (
b0 r
b0 ?
b0 [
0:
1'
b0 =
b0 Q
b0 m
0&
b0 -
b0 O
b0 t
b0 .
b0 \
b0 u
b0 @
b0 M
b0 Z
b0 >
b0 N
04
0;
b1101111 X
b1000 )
b1000 q
b0 *
b0 p
b0 /
b0 s
b1101111 2
b1101111 C
b100000000000000001101111 6
b100000000000000001101111 S
b100000000000000001101111 W
b11100 0
b11100 n
b11000 !
b11000 %
b11000 1
b11000 T
b11000 o
1"
#60
0"
#65
b11111111111111111111101111101110 (
b11111111111111111111101111101110 r
0'
b11111111111111111111101111101110 =
b11111111111111111111101111101110 Q
b11111111111111111111101111101110 m
b11111111111111111111101111101110 ?
b11111111111111111111101111101110 [
b10 >
b10 N
1<
1+
b11111111111111111111101111101110 7
b11111111111111111111101111101110 Y
b10011 X
b1011111 8
b1011111 B
b1110 )
b1110 q
b11110 *
b11110 p
b1110 /
b1110 s
b10011 2
b10011 C
b10111110111011110000011100010011 6
b10111110111011110000011100010011 S
b10111110111011110000011100010011 W
b100000 0
b100000 n
b11100 !
b11100 %
b11100 1
b11100 T
b11100 o
1"
#70
0"
#75
1'
b0 =
b0 Q
b0 m
b0 (
b0 r
b0 ?
b0 [
b0 >
b0 N
x4
13
0+
b0 7
b0 Y
b100011 X
b0 8
b0 B
b111 *
b111 p
b10 9
b10 A
b0 /
b0 s
b100011 2
b100011 C
b11111111111111111111101111101110 -
b11111111111111111111101111101110 O
b11111111111111111111101111101110 t
b111000111010000000100011 6
b111000111010000000100011 S
b111000111010000000100011 W
b100100 0
b100100 n
b100000 !
b100000 %
b100000 1
b100000 T
b100000 o
1"
#80
0"
#85
b10100 ?
b10100 [
b10100 -
b10100 O
b10100 t
b10100 .
b10100 \
b10100 u
b1011 @
b1011 M
b1011 Z
b1 >
b1 N
0<
1;
03
b1000 7
b1000 Y
b1100011 X
b11 )
b11 q
b11 *
b11 p
b1 9
b1 A
b1000 /
b1000 s
b1100011 2
b1100011 C
b1100011001010001100011 6
b1100011001010001100011 S
b1100011001010001100011 W
b101000 0
b101000 n
b100100 !
b100100 %
b100100 1
b100100 T
b100100 o
1"
#90
0"
#95
b11111111111111111111110010101111 (
b11111111111111111111110010101111 r
0'
b11111111111111111111110010101111 =
b11111111111111111111110010101111 Q
b11111111111111111111110010101111 m
b11111111111111111111110010101111 ?
b11111111111111111111110010101111 [
b0 -
b0 O
b0 t
b0 .
b0 \
b0 u
b0 @
b0 M
b0 Z
b10 >
b10 N
1<
04
0;
1+
b11111111111111111111110010101111 7
b11111111111111111111110010101111 Y
b10011 X
b1100101 8
b1100101 B
b1111 )
b1111 q
b11100 *
b11100 p
b0 9
b0 A
b1110 /
b1110 s
b10011 2
b10011 C
b11001010111111100000011100010011 6
b11001010111111100000011100010011 S
b11001010111111100000011100010011 W
b101100 0
b101100 n
b101000 !
b101000 %
b101000 1
b101000 T
b101000 o
1"
#100
0"
#105
b0 (
b0 r
1'
b0 =
b0 Q
b0 m
b0 ?
b0 [
b0 >
b0 N
0<
0+
b1000 7
b1000 Y
b1101111 X
b0 8
b0 B
b1000 )
b1000 q
b0 *
b0 p
b0 /
b0 s
b1101111 2
b1101111 C
b100000000000000001101111 6
b100000000000000001101111 S
b100000000000000001101111 W
b110000 0
b110000 n
b101100 !
b101100 %
b101100 1
b101100 T
b101100 o
1"
#110
0"
#115
b11111111111111111111110111101010 (
b11111111111111111111110111101010 r
0'
b11111111111111111111110111101010 =
b11111111111111111111110111101010 Q
b11111111111111111111110111101010 m
b11111111111111111111110111101010 ?
b11111111111111111111110111101010 [
b10 >
b10 N
1<
1+
b11111111111111111111110111101010 7
b11111111111111111111110111101010 Y
b10011 X
b1101111 8
b1101111 B
b1010 )
b1010 q
b11010 *
b11010 p
b1110 /
b1110 s
b10011 2
b10011 C
b11011110101011010000011100010011 6
b11011110101011010000011100010011 S
b11011110101011010000011100010011 W
b110100 0
b110100 n
b110000 !
b110000 %
b110000 1
b110000 T
b110000 o
1"
#120
0"
#125
b100 =
b100 Q
b100 m
b0x00 (
b0x00 r
b100 ?
b100 [
b11111111111111111111110111101010 -
b11111111111111111111110111101010 O
b11111111111111111111110111101010 t
b0 >
b0 N
x4
13
0+
b100 7
b100 Y
b100011 X
b0 8
b0 B
b1110 )
b1110 q
b111 *
b111 p
b10 9
b10 A
b100 /
b100 s
b100011 2
b100011 C
b111000111010001000100011 6
b111000111010001000100011 S
b111000111010001000100011 W
b111000 0
b111000 n
b110100 !
b110100 %
b110100 1
b110100 T
b110100 o
1"
#130
0"
#135
1'
b0 =
b0 Q
b0 m
b0 (
b0 r
b0 ?
b0 [
b0 -
b0 O
b0 t
0<
04
03
b0 7
b0 Y
b1101111 X
b0 )
b0 q
b0 *
b0 p
b0 9
b0 A
b0 /
b0 s
b1101111 2
b1101111 C
b1101111 6
b1101111 S
b1101111 W
b111100 0
b111100 n
b111000 !
b111000 %
b111000 1
b111000 T
b111000 o
1"
#140
0"
#145
b0 X
b0 2
b0 C
b0 6
b0 S
b0 W
b1000000 0
b1000000 n
b111100 !
b111100 %
b111100 1
b111100 T
b111100 o
1"
#150
0"
#155
b1000100 0
b1000100 n
b1000000 !
b1000000 %
b1000000 1
b1000000 T
b1000000 o
1"
#160
0"
#165
b1001000 0
b1001000 n
b1000100 !
b1000100 %
b1000100 1
b1000100 T
b1000100 o
1"
#170
0"
#175
b1001100 0
b1001100 n
b1001000 !
b1001000 %
b1001000 1
b1001000 T
b1001000 o
1"
#180
0"
#185
b1010000 0
b1010000 n
b1001100 !
b1001100 %
b1001100 1
b1001100 T
b1001100 o
1"
#190
0"
#195
b1010100 0
b1010100 n
b1010000 !
b1010000 %
b1010000 1
b1010000 T
b1010000 o
1"
#200
0"
#205
b1011000 0
b1011000 n
b1010100 !
b1010100 %
b1010100 1
b1010100 T
b1010100 o
1"
#210
0"
#215
b1011100 0
b1011100 n
b1011000 !
b1011000 %
b1011000 1
b1011000 T
b1011000 o
1"
#220
0"
#225
b1100000 0
b1100000 n
b1011100 !
b1011100 %
b1011100 1
b1011100 T
b1011100 o
1"
#230
0"
#235
b1100100 0
b1100100 n
b1100000 !
b1100000 %
b1100000 1
b1100000 T
b1100000 o
1"
#240
0"
#245
b1101000 0
b1101000 n
b1100100 !
b1100100 %
b1100100 1
b1100100 T
b1100100 o
1"
#250
0"
#255
b1101100 0
b1101100 n
b1101000 !
b1101000 %
b1101000 1
b1101000 T
b1101000 o
1"
#260
0"
#265
b1110000 0
b1110000 n
b1101100 !
b1101100 %
b1101100 1
b1101100 T
b1101100 o
1"
#270
0"
#275
b1110100 0
b1110100 n
b1110000 !
b1110000 %
b1110000 1
b1110000 T
b1110000 o
1"
#280
0"
#285
b1111000 0
b1111000 n
b1110100 !
b1110100 %
b1110100 1
b1110100 T
b1110100 o
1"
#290
0"
#295
b1111100 0
b1111100 n
b1111000 !
b1111000 %
b1111000 1
b1111000 T
b1111000 o
1"
#300
0"
#305
b10000000 0
b10000000 n
b1111100 !
b1111100 %
b1111100 1
b1111100 T
b1111100 o
1"
#310
0"
#315
b10000100 0
b10000100 n
b10000000 !
b10000000 %
b10000000 1
b10000000 T
b10000000 o
1"
#320
0"
#325
b10001000 0
b10001000 n
b10000100 !
b10000100 %
b10000100 1
b10000100 T
b10000100 o
1"
#330
0"
#335
b10001100 0
b10001100 n
b10001000 !
b10001000 %
b10001000 1
b10001000 T
b10001000 o
1"
#340
0"
#345
b10010000 0
b10010000 n
b10001100 !
b10001100 %
b10001100 1
b10001100 T
b10001100 o
1"
#350
0"
#355
b10010100 0
b10010100 n
b10010000 !
b10010000 %
b10010000 1
b10010000 T
b10010000 o
1"
#360
0"
#365
b10011000 0
b10011000 n
b10010100 !
b10010100 %
b10010100 1
b10010100 T
b10010100 o
1"
#370
0"
#375
b10011100 0
b10011100 n
b10011000 !
b10011000 %
b10011000 1
b10011000 T
b10011000 o
1"
#380
0"
#385
b10100000 0
b10100000 n
b10011100 !
b10011100 %
b10011100 1
b10011100 T
b10011100 o
1"
#390
0"
#395
b10100100 0
b10100100 n
b10100000 !
b10100000 %
b10100000 1
b10100000 T
b10100000 o
1"
#400
0"
#405
b10101000 0
b10101000 n
b10100100 !
b10100100 %
b10100100 1
b10100100 T
b10100100 o
1"
#410
0"
#415
b10101100 0
b10101100 n
b10101000 !
b10101000 %
b10101000 1
b10101000 T
b10101000 o
1"
#420
0"
#425
b10110000 0
b10110000 n
b10101100 !
b10101100 %
b10101100 1
b10101100 T
b10101100 o
1"
#430
0"
#435
b10110100 0
b10110100 n
b10110000 !
b10110000 %
b10110000 1
b10110000 T
b10110000 o
1"
#440
0"
#445
b10111000 0
b10111000 n
b10110100 !
b10110100 %
b10110100 1
b10110100 T
b10110100 o
1"
#450
0"
#455
b10111100 0
b10111100 n
b10111000 !
b10111000 %
b10111000 1
b10111000 T
b10111000 o
1"
#460
0"
#465
b11000000 0
b11000000 n
b10111100 !
b10111100 %
b10111100 1
b10111100 T
b10111100 o
1"
#470
0"
#475
b11000100 0
b11000100 n
b11000000 !
b11000000 %
b11000000 1
b11000000 T
b11000000 o
1"
#480
0"
#485
b11001000 0
b11001000 n
b11000100 !
b11000100 %
b11000100 1
b11000100 T
b11000100 o
1"
#490
0"
#495
b11001100 0
b11001100 n
b11001000 !
b11001000 %
b11001000 1
b11001000 T
b11001000 o
1"
#500
0"
#505
b11010000 0
b11010000 n
b11001100 !
b11001100 %
b11001100 1
b11001100 T
b11001100 o
1"
#510
0"
#515
b11010100 0
b11010100 n
b11010000 !
b11010000 %
b11010000 1
b11010000 T
b11010000 o
1"
#520
0"
#525
b11011000 0
b11011000 n
b11010100 !
b11010100 %
b11010100 1
b11010100 T
b11010100 o
1"
#530
0"
#535
b11011100 0
b11011100 n
b11011000 !
b11011000 %
b11011000 1
b11011000 T
b11011000 o
1"
#540
0"
#545
b11100000 0
b11100000 n
b11011100 !
b11011100 %
b11011100 1
b11011100 T
b11011100 o
1"
#550
0"
#555
b11100100 0
b11100100 n
b11100000 !
b11100000 %
b11100000 1
b11100000 T
b11100000 o
1"
#560
0"
#565
b11101000 0
b11101000 n
b11100100 !
b11100100 %
b11100100 1
b11100100 T
b11100100 o
1"
#570
0"
#575
b11101100 0
b11101100 n
b11101000 !
b11101000 %
b11101000 1
b11101000 T
b11101000 o
1"
#580
0"
#585
b11110000 0
b11110000 n
b11101100 !
b11101100 %
b11101100 1
b11101100 T
b11101100 o
1"
#590
0"
