data_memory.v
module data_memory (
    input wire clk,
    input wire mem_read,
    input wire mem_write,
    input wire [31:0] address,
    input wire [31:0] write_data,
    output wire [31:0] read_data
);

    // Memory array (1KB for simplicity)
    reg [31:0] memory [0:255];
    integer i;
    
    // Initialize memory to 0
    initial begin
        for (i = 0; i < 256; i = i + 1)
            memory[i] = 32'h0;
    end
    
    // Write operation (synchronous)
    always @(posedge clk) begin
        if (mem_write)
            memory[address[9:2]] <= write_data;
    end
    
    // Read operation (asynchronous)
    assign read_data = mem_read ? memory[address[9:2]] : 32'h0;

endmodule

src/core/alu.v
module alu (
    input wire [31:0] a,
    input wire [31:0] b,
    input wire [3:0] alu_control,
    output reg [31:0] result,
    output wire zero
);

    // ALU control codes
    parameter ALU_ADD = 4'b0000;
    parameter ALU_SUB = 4'b0001;
    parameter ALU_AND = 4'b0010;
    parameter ALU_OR  = 4'b0011;
    parameter ALU_XOR = 4'b0100;
    parameter ALU_SLL = 4'b0101; // Shift left logical
    parameter ALU_SRL = 4'b0110; // Shift right logical
    parameter ALU_SRA = 4'b0111; // Shift right arithmetic
    parameter ALU_SLT = 4'b1000; // Set less than (signed)
    parameter ALU_SLTU = 4'b1001; // Set less than unsigned
    
    // ALU operation
    always @(*) begin
        case (alu_control)
            ALU_ADD: result = a + b;
            ALU_SUB: result = a - b;
            ALU_AND: result = a & b;
            ALU_OR:  result = a | b;
            ALU_XOR: result = a ^ b;
            ALU_SLL: result = a << b[4:0];
            ALU_SRL: result = a >> b[4:0];
            ALU_SRA: result = $signed(a) >>> b[4:0];
            ALU_SLT: result = ($signed(a) < $signed(b)) ? 32'h1 : 32'h0;
            ALU_SLTU: result = (a < b) ? 32'h1 : 32'h0;
            default: result = 32'h0;
        endcase
    end
    
    // Zero flag
    assign zero = (result == 32'h0);

endmodule

immediate_generator.v
module immediate_generator (
    input wire [31:0] instruction,
    output reg [31:0] imm_extended
);

    wire [6:0] opcode = instruction[6:0];
    
    always @(*) begin
        case(opcode)
            7'b0010011, // I-type ALU operations
            7'b0000011: // I-type loads
                imm_extended = {{20{instruction[31]}}, instruction[31:20]};
                
            7'b0100011: // S-type
                imm_extended = {{20{instruction[31]}}, instruction[31:25], instruction[11:7]};
                
            7'b1100011: // B-type
                imm_extended = {{20{instruction[31]}}, instruction[7], instruction[30:25], instruction[11:8], 1'b0};
                
            7'b0110111, // U-type LUI
            7'b0010111: // U-type AUIPC
                imm_extended = {instruction[31:12], 12'h000};
                
            7'b1101111: // J-type JAL
                imm_extended = {{12{instruction[31]}}, instruction[19:12], instruction[20], instruction[30:21], 1'b0};
                
            default:
                imm_extended = 32'h0;
        endcase
    end

endmodule

register_file.v
module register_file (
    input wire clk,
    input wire rst_n,
    input wire reg_write,
    input wire [4:0] read_reg1,
    input wire [4:0] read_reg2,
    input wire [4:0] write_reg,
    input wire [31:0] write_data,
    output wire [31:0] read_data1,
    output wire [31:0] read_data2
);

    // 32 registers, each 32-bit wide
    reg [31:0] registers [0:31];
    integer i;
    
    // Initialize all registers to 0
    initial begin
        for (i = 0; i < 32; i = i + 1)
            registers[i] = 32'h0;
    end
    
    // Write operation (at positive clock edge)
    always @(posedge clk) begin
        if (reg_write && write_reg != 0) // Register x0 must always be 0
            registers[write_reg] <= write_data;
    end
    
    // Read operations (combinational)
    assign read_data1 = (read_reg1 == 0) ? 32'h0 : registers[read_reg1];
    assign read_data2 = (read_reg2 == 0) ? 32'h0 : registers[read_reg2];

endmodule

control_unit.v
module control_unit (
    input wire [6:0] opcode,
    input wire [2:0] funct3,
    input wire [6:0] funct7,
    output reg reg_write,
    output reg mem_read,
    output reg mem_write,
    output reg branch,
    output reg mem_to_reg,
    output reg alu_src,
    output reg [1:0] alu_op,
    output reg [3:0] alu_control
);

    // RISC-V opcode definitions
    parameter R_TYPE     = 7'b0110011;
    parameter I_TYPE_ALU = 7'b0010011;
    parameter I_TYPE_LOAD = 7'b0000011;
    parameter S_TYPE     = 7'b0100011;
    parameter B_TYPE     = 7'b1100011;
    parameter U_TYPE_LUI = 7'b0110111;
    parameter U_TYPE_AUIPC = 7'b0010111;
    parameter J_TYPE_JAL = 7'b1101111;
    parameter I_TYPE_JALR = 7'b1100111;
    
    // Main control signals
    always @(*) begin
        case(opcode)
            R_TYPE: begin
                reg_write = 1'b1;
                mem_read = 1'b0;
                mem_write = 1'b0;
                branch = 1'b0;
                mem_to_reg = 1'b0;
                alu_src = 1'b0;
                alu_op = 2'b10;
            end
            I_TYPE_ALU: begin
                reg_write = 1'b1;
                mem_read = 1'b0;
                mem_write = 1'b0;
                branch = 1'b0;
                mem_to_reg = 1'b0;
                alu_src = 1'b1;
                alu_op = 2'b10;
            end
            I_TYPE_LOAD: begin
                reg_write = 1'b1;
                mem_read = 1'b1;
                mem_write = 1'b0;
                branch = 1'b0;
                mem_to_reg = 1'b1;
                alu_src = 1'b1;
                alu_op = 2'b00;
            end
            S_TYPE: begin
                reg_write = 1'b0;
                mem_read = 1'b0;
                mem_write = 1'b1;
                branch = 1'b0;
                mem_to_reg = 1'bx; // Don't care
                alu_src = 1'b1;
                alu_op = 2'b00;
            end
            B_TYPE: begin
                reg_write = 1'b0;
                mem_read = 1'b0;
                mem_write = 1'b0;
                branch = 1'b1;
                mem_to_reg = 1'bx; // Don't care
                alu_src = 1'b0;
                alu_op = 2'b01;
            end
            default: begin
                reg_write = 1'b0;
                mem_read = 1'b0;
                mem_write = 1'b0;
                branch = 1'b0;
                mem_to_reg = 1'b0;
                alu_src = 1'b0;
                alu_op = 2'b00;
            end
        endcase
    end

    // ALU control logic
    always @(*) begin
        case(alu_op)
            2'b00: alu_control = 4'b0000; // ADD for loads/stores
            2'b01: alu_control = 4'b0001; // SUB for branches
            2'b10: begin // R-type or I-type ALU
                case(funct3)
                    3'b000: begin
                        // ADD or SUB (for R-type)
                        if (opcode == R_TYPE && funct7 == 7'b0100000)
                            alu_control = 4'b0001; // SUB
                        else
                            alu_control = 4'b0000; // ADD
                    end
                    3'b001: alu_control = 4'b0101; // SLL
                    3'b010: alu_control = 4'b1000; // SLT
                    3'b011: alu_control = 4'b1001; // SLTU
                    3'b100: alu_control = 4'b0100; // XOR
                    3'b101: begin
                        if (funct7 == 7'b0100000)
                            alu_control = 4'b0111; // SRA
                        else
                            alu_control = 4'b0110; // SRL
                    end
                    3'b110: alu_control = 4'b0011; // OR
                    3'b111: alu_control = 4'b0010; // AND
                    default: alu_control = 4'b0000;
                endcase
            end
            default: alu_control = 4'b0000;
        endcase
    end

endmodule

instruction_memory.v
module instruction_memory (
    input wire [31:0] pc,
    output wire [31:0] instruction
);

    // For a simple implementation, we'll use a small ROM
    reg [31:0] memory [0:255]; // 256 words of memory
    integer i;
    
    // Initialize with a simple program (can be replaced with actual instructions)
    initial begin
        // Example program:
        // addi x1, x0, 5      # x1 = 5
        // addi x2, x0, 10     # x2 = 10
        // add x3, x1, x2      # x3 = x1 + x2 = 15
        // sw x3, 0(x0)        # Store x3 to memory address 0
        // lw x4, 0(x0)        # Load from memory address 0 to x4
        memory[0] = 32'h00500093;  // addi x1, x0, 5
        memory[1] = 32'h00A00113;  // addi x2, x0, 10
        memory[2] = 32'h002081B3;  // add x3, x1, x2
        memory[3] = 32'h00302023;  // sw x3, 0(x0)
        memory[4] = 32'h00002203;  // lw x4, 0(x0)
        // Rest of memory initialized to 0
        for (i = 5; i < 256; i = i + 1)
            memory[i] = 32'h0;
    end
    
    // Word-aligned access (address ignores lower 2 bits)
    assign instruction = memory[pc[9:2]]; // PC is byte-addressed, but memory is word-addressed

endmodule

program_counter.v
module program_counter (
    input wire clk,
    input wire rst_n,
    input wire [31:0] pc_next,
    output reg [31:0] pc_current
);

    always @(posedge clk or negedge rst_n) begin
        if (!rst_n)
            pc_current <= 32'h0;
        else
            pc_current <= pc_next;
    end

endmodule

src/core/riscv_cpu.v
module riscv_cpu (
    input wire clk,
    input wire rst_n,
    output wire [31:0] pc_out
);
    // Wires for connecting components
    wire [31:0] pc_current;
    wire [31:0] pc_next;
    wire [31:0] instruction;
    wire [31:0] alu_result;
    wire [31:0] read_data1, read_data2;
    wire [31:0] imm_extended;
    wire [31:0] write_data;
    wire [31:0] read_data_mem;
    wire [4:0] rd, rs1, rs2;
    wire [2:0] funct3;
    wire [6:0] funct7;
    wire [6:0] opcode;
    
    // Control signals
    wire reg_write;
    wire mem_read;
    wire mem_write;
    wire branch;
    wire mem_to_reg;
    wire alu_src;
    wire [1:0] alu_op;
    wire [3:0] alu_control;
    wire zero_flag;
    wire pc_src;
    
    // Program Counter
    program_counter pc (
        .clk(clk),
        .rst_n(rst_n),
        .pc_next(pc_next),
        .pc_current(pc_current)
    );
    
    // Instruction Memory
    instruction_memory imem (
        .pc(pc_current),
        .instruction(instruction)
    );
    
    // Instruction decoding
    assign opcode = instruction[6:0];
    assign rd = instruction[11:7];
    assign funct3 = instruction[14:12];
    assign rs1 = instruction[19:15];
    assign rs2 = instruction[24:20];
    assign funct7 = instruction[31:25];
    
    // Control Unit
    control_unit cu (
        .opcode(opcode),
        .funct3(funct3),
        .funct7(funct7),
        .reg_write(reg_write),
        .mem_read(mem_read),
        .mem_write(mem_write),
        .branch(branch),
        .mem_to_reg(mem_to_reg),
        .alu_src(alu_src),
        .alu_op(alu_op),
        .alu_control(alu_control)
    );
    
    // Register File
    register_file rf (
        .clk(clk),
        .rst_n(rst_n),
        .reg_write(reg_write),
        .read_reg1(rs1),
        .read_reg2(rs2),
        .write_reg(rd),
        .write_data(write_data),
        .read_data1(read_data1),
        .read_data2(read_data2)
    );
    
    // Immediate Generator
    immediate_generator immgen (
        .instruction(instruction),
        .imm_extended(imm_extended)
    );
    
    // ALU source mux
    wire [31:0] alu_input2 = alu_src ? imm_extended : read_data2;
    
    // ALU
    alu main_alu (
        .a(read_data1),
        .b(alu_input2),
        .alu_control(alu_control),
        .result(alu_result),
        .zero(zero_flag)
    );
    
    // Data Memory
    data_memory dmem (
        .clk(clk),
        .mem_read(mem_read),
        .mem_write(mem_write),
        .address(alu_result),
        .write_data(read_data2),
        .read_data(read_data_mem)
    );
    
    // Write back mux
    assign write_data = mem_to_reg ? read_data_mem : alu_result;
    
    // Branch logic
    assign pc_src = branch & zero_flag;
    assign pc_next = pc_src ? (pc_current + imm_extended) : (pc_current + 4);
    
    // Output
    assign pc_out = pc_current;
    
endmodule

src/testbench/tb_riscv_cpu.v
module tb_riscv_cpu;
    reg clk;
    reg rst_n;
    wire [31:0] pc_out;
    integer i;
    
    // Instantiate the RISC-V CPU
    riscv_cpu dut (
        .clk(clk),
        .rst_n(rst_n),
        .pc_out(pc_out)
    );
    
    // Clock generation
    initial begin
        clk = 0;
        forever #5 clk = ~clk;
    end
    
    // Waveform dumping
    initial begin
        $dumpfile("waveform.vcd");
        $dumpvars(0, tb_riscv_cpu);
    end
    
    // Test sequence
    initial begin
        $display("Starting RISC-V CPU test...");
        
        // Reset the CPU
        rst_n = 0;
        #10;
        rst_n = 1;
        
        // Run longer to allow all instructions to execute
        #1500;  // Increased from 1000 to 1500
        
        // Print register file contents at end
        $display("\nFinal Register File Contents:");
        for (i = 0; i < 10; i = i + 1) begin
            $display("x%0d = %0d (0x%h)", i, dut.rf.registers[i], dut.rf.registers[i]);
        end
        
        // Print Fibonacci sequence from memory
        $display("\nFibonacci Sequence in Memory:");
        for (i = 0; i < 8; i = i + 1) begin
            $display("mem[%0d] = %0d (0x%h)", i, dut.dmem.memory[i], dut.dmem.memory[i]);
        end
        
        // End simulation
        $display("\nEnd of test. PC = %h", pc_out);
        $finish;
    end
    
endmodule

waveform.vcd
$date
	Mon Apr 14 16:40:19 2025
$end
$version
	Icarus Verilog
$end
$timescale
	1s
$end
$scope module tb_riscv_cpu $end
$var wire 32 ! pc_out [31:0] $end
$var reg 1 " clk $end
$var reg 1 # rst_n $end
$var integer 32 $ i [31:0] $end
$scope module dut $end
$var wire 1 " clk $end
$var wire 32 % pc_out [31:0] $end
$var wire 1 & pc_src $end
$var wire 1 # rst_n $end
$var wire 1 ' zero_flag $end
$var wire 32 ( write_data [31:0] $end
$var wire 5 ) rs2 [4:0] $end
$var wire 5 * rs1 [4:0] $end
$var wire 1 + reg_write $end
$var wire 32 , read_data_mem [31:0] $end
$var wire 32 - read_data2 [31:0] $end
$var wire 32 . read_data1 [31:0] $end
$var wire 5 / rd [4:0] $end
$var wire 32 0 pc_next [31:0] $end
$var wire 32 1 pc_current [31:0] $end
$var wire 7 2 opcode [6:0] $end
$var wire 1 3 mem_write $end
$var wire 1 4 mem_to_reg $end
$var wire 1 5 mem_read $end
$var wire 32 6 instruction [31:0] $end
$var wire 32 7 imm_extended [31:0] $end
$var wire 7 8 funct7 [6:0] $end
$var wire 3 9 funct3 [2:0] $end
$var wire 1 : branch $end
$var wire 1 ; alu_src $end
$var wire 32 < alu_result [31:0] $end
$var wire 2 = alu_op [1:0] $end
$var wire 32 > alu_input2 [31:0] $end
$var wire 4 ? alu_control [3:0] $end
$scope module cu $end
$var wire 3 @ funct3 [2:0] $end
$var wire 7 A funct7 [6:0] $end
$var wire 7 B opcode [6:0] $end
$var parameter 7 C B_TYPE $end
$var parameter 7 D I_TYPE_ALU $end
$var parameter 7 E I_TYPE_JALR $end
$var parameter 7 F I_TYPE_LOAD $end
$var parameter 7 G J_TYPE_JAL $end
$var parameter 7 H R_TYPE $end
$var parameter 7 I S_TYPE $end
$var parameter 7 J U_TYPE_AUIPC $end
$var parameter 7 K U_TYPE_LUI $end
$var reg 4 L alu_control [3:0] $end
$var reg 2 M alu_op [1:0] $end
$var reg 1 ; alu_src $end
$var reg 1 : branch $end
$var reg 1 5 mem_read $end
$var reg 1 4 mem_to_reg $end
$var reg 1 3 mem_write $end
$var reg 1 + reg_write $end
$upscope $end
$scope module dmem $end
$var wire 1 " clk $end
$var wire 1 5 mem_read $end
$var wire 1 3 mem_write $end
$var wire 32 N write_data [31:0] $end
$var wire 32 O read_data [31:0] $end
$var wire 32 P address [31:0] $end
$var integer 32 Q i [31:0] $end
$upscope $end
$scope module imem $end
$var wire 32 R instruction [31:0] $end
$var wire 32 S pc [31:0] $end
$var integer 32 T i [31:0] $end
$upscope $end
$scope module immgen $end
$var wire 32 U instruction [31:0] $end
$var wire 7 V opcode [6:0] $end
$var reg 32 W imm_extended [31:0] $end
$upscope $end
$scope module main_alu $end
$var wire 4 X alu_control [3:0] $end
$var wire 32 Y b [31:0] $end
$var wire 1 ' zero $end
$var wire 32 Z a [31:0] $end
$var parameter 4 [ ALU_ADD $end
$var parameter 4 \ ALU_AND $end
$var parameter 4 ] ALU_OR $end
$var parameter 4 ^ ALU_SLL $end
$var parameter 4 _ ALU_SLT $end
$var parameter 4 ` ALU_SLTU $end
$var parameter 4 a ALU_SRA $end
$var parameter 4 b ALU_SRL $end
$var parameter 4 c ALU_SUB $end
$var parameter 4 d ALU_XOR $end
$var reg 32 e result [31:0] $end
$upscope $end
$scope module pc $end
$var wire 1 " clk $end
$var wire 32 f pc_next [31:0] $end
$var wire 1 # rst_n $end
$var reg 32 g pc_current [31:0] $end
$upscope $end
$scope module rf $end
$var wire 1 " clk $end
$var wire 5 h read_reg1 [4:0] $end
$var wire 5 i read_reg2 [4:0] $end
$var wire 1 + reg_write $end
$var wire 1 # rst_n $end
$var wire 32 j write_data [31:0] $end
$var wire 5 k write_reg [4:0] $end
$var wire 32 l read_data2 [31:0] $end
$var wire 32 m read_data1 [31:0] $end
$var integer 32 n i [31:0] $end
$upscope $end
$upscope $end
$upscope $end
$enddefinitions $end
$comment Show the parameter values. $end
$dumpall
b100 d
b1 c
b110 b
b111 a
b1001 `
b1000 _
b101 ^
b11 ]
b10 \
b0 [
b110111 K
b10111 J
b100011 I
b110011 H
b1101111 G
b11 F
b1100111 E
b10011 D
b1100011 C
$end
#0
$dumpvars
b100000 n
b0 m
b0 l
b1 k
b101 j
b101 i
b0 h
b0 g
b100 f
b101 e
b0 Z
b101 Y
b0 X
b101 W
b10011 V
b10100000000000010010011 U
b100000000 T
b0 S
b10100000000000010010011 R
b100000000 Q
b101 P
b0 O
b0 N
b10 M
b0 L
b10011 B
b0 A
b0 @
b0 ?
b101 >
b10 =
b101 <
1;
0:
b0 9
b0 8
b101 7
b10100000000000010010011 6
05
04
03
b10011 2
b0 1
b100 0
b1 /
b0 .
b0 -
b0 ,
1+
b0 *
b101 )
b101 (
0'
0&
b0 %
bx $
0#
0"
b0 !
$end
#5
1"
#10
0"
1#
#15
b1010 (
b1010 j
b1010 <
b1010 P
b1010 e
b1010 >
b1010 Y
b1010 7
b1010 W
b1010 )
b1010 i
b10 /
b10 k
b101000000000000100010011 6
b101000000000000100010011 R
b101000000000000100010011 U
b1000 0
b1000 f
b100 !
b100 %
b100 1
b100 S
b100 g
1"
#20
0"
#25
b1111 (
b1111 j
b1111 <
b1111 P
b1111 e
b1010 -
b1010 N
b1010 l
b101 .
b101 Z
b101 m
0;
b0 7
b0 W
b110011 V
b10 )
b10 i
b1 *
b1 h
b11 /
b11 k
b110011 2
b110011 B
b1000001000000110110011 6
b1000001000000110110011 R
b1000001000000110110011 U
b1100 0
b1100 f
b1000 !
b1000 %
b1000 1
b1000 S
b1000 g
1"
#30
0"
#35
1'
b0 <
b0 P
b0 e
b0 >
b0 Y
b0 (
b0 j
b1111 -
b1111 N
b1111 l
b0 .
b0 Z
b0 m
b0 =
b0 M
1;
x4
13
0+
b100011 V
b11 )
b11 i
b0 *
b0 h
b10 9
b10 @
b0 /
b0 k
b100011 2
b100011 B
b1100000010000000100011 6
b1100000010000000100011 R
b1100000010000000100011 U
b10000 0
b10000 f
b1100 !
b1100 %
b1100 1
b1100 S
b1100 g
1"
#40
0"
#45
b1111 (
b1111 j
b1111 ,
b1111 O
b0 -
b0 N
b0 l
14
03
15
1+
b11 V
b0 )
b0 i
b100 /
b100 k
b11 2
b11 B
b10001000000011 6
b10001000000011 R
b10001000000011 U
b10100 0
b10100 f
b10000 !
b10000 %
b10000 1
b10000 S
b10000 g
1"
#50
0"
#55
b0 (
b0 j
b0 ,
b0 O
0;
04
05
0+
b0 V
b0 9
b0 @
b0 /
b0 k
b0 2
b0 B
b0 6
b0 R
b0 U
b11000 0
b11000 f
b10100 !
b10100 %
b10100 1
b10100 S
b10100 g
1"
#60
0"
#65
b11100 0
b11100 f
b11000 !
b11000 %
b11000 1
b11000 S
b11000 g
1"
#70
0"
#75
b100000 0
b100000 f
b11100 !
b11100 %
b11100 1
b11100 S
b11100 g
1"
#80
0"
#85
b100100 0
b100100 f
b100000 !
b100000 %
b100000 1
b100000 S
b100000 g
1"
#90
0"
#95
b101000 0
b101000 f
b100100 !
b100100 %
b100100 1
b100100 S
b100100 g
1"
#100
0"
#105
b101100 0
b101100 f
b101000 !
b101000 %
b101000 1
b101000 S
b101000 g
1"
#110
0"
#115
b110000 0
b110000 f
b101100 !
b101100 %
b101100 1
b101100 S
b101100 g
1"
#120
0"
#125
b110100 0
b110100 f
b110000 !
b110000 %
b110000 1
b110000 S
b110000 g
1"
#130
0"
#135
b111000 0
b111000 f
b110100 !
b110100 %
b110100 1
b110100 S
b110100 g
1"
#140
0"
#145
b111100 0
b111100 f
b111000 !
b111000 %
b111000 1
b111000 S
b111000 g
1"
#150
0"
#155
b1000000 0
b1000000 f
b111100 !
b111100 %
b111100 1
b111100 S
b111100 g
1"
#160
0"
#165
b1000100 0
b1000100 f
b1000000 !
b1000000 %
b1000000 1
b1000000 S
b1000000 g
1"
#170
0"
#175
b1001000 0
b1001000 f
b1000100 !
b1000100 %
b1000100 1
b1000100 S
b1000100 g
1"
#180
0"
#185
b1001100 0
b1001100 f
b1001000 !
b1001000 %
b1001000 1
b1001000 S
b1001000 g
1"
#190
0"
#195
b1010000 0
b1010000 f
b1001100 !
b1001100 %
b1001100 1
b1001100 S
b1001100 g
1"
#200
0"
#205
b1010100 0
b1010100 f
b1010000 !
b1010000 %
b1010000 1
b1010000 S
b1010000 g
1"
#210
0"
b101 $
