data_memory.v
module data_memory (
    input wire clk,
    input wire mem_read,
    input wire mem_write,
    input wire [31:0] address,
    input wire [31:0] write_data,
    output wire [31:0] read_data
);

    // Memory array (1KB for simplicity)
    reg [31:0] memory [0:255];
    integer i;
    
    // Initialize memory to 0
    initial begin
        for (i = 0; i < 256; i = i + 1)
            memory[i] = 32'h0;
    end
    
    // Write operation (synchronous)
    always @(posedge clk) begin
        if (mem_write)
            memory[address[9:2]] <= write_data;
    end
    
    // Read operation (asynchronous)
    assign read_data = mem_read ? memory[address[9:2]] : 32'h0;

endmodule

src/core/alu.v
module alu (
    input wire [31:0] a,
    input wire [31:0] b,
    input wire [3:0] alu_control,
    output reg [31:0] result,
    output wire zero
);

    // ALU control codes
    parameter ALU_ADD = 4'b0000;
    parameter ALU_SUB = 4'b0001;
    parameter ALU_AND = 4'b0010;
    parameter ALU_OR  = 4'b0011;
    parameter ALU_XOR = 4'b0100;
    parameter ALU_SLL = 4'b0101; // Shift left logical
    parameter ALU_SRL = 4'b0110; // Shift right logical
    parameter ALU_SRA = 4'b0111; // Shift right arithmetic
    parameter ALU_SLT = 4'b1000; // Set less than (signed)
    parameter ALU_SLTU = 4'b1001; // Set less than unsigned
    
    // ALU operation
    always @(*) begin
        case (alu_control)
            ALU_ADD: result = a + b;
            ALU_SUB: result = a - b;
            ALU_AND: result = a & b;
            ALU_OR:  result = a | b;
            ALU_XOR: result = a ^ b;
            ALU_SLL: result = a << b[4:0];
            ALU_SRL: result = a >> b[4:0];
            ALU_SRA: result = $signed(a) >>> b[4:0];
            ALU_SLT: result = ($signed(a) < $signed(b)) ? 32'h1 : 32'h0;
            ALU_SLTU: result = (a < b) ? 32'h1 : 32'h0;
            default: result = 32'h0;
        endcase
    end
    
    // Zero flag
    assign zero = (result == 32'h0);

endmodule

immediate_generator.v
module immediate_generator (
    input wire [31:0] instruction,
    output reg [31:0] imm_extended
);

    wire [6:0] opcode = instruction[6:0];
    
    always @(*) begin
        case(opcode)
            7'b0010011, // I-type ALU operations
            7'b0000011: // I-type loads
                imm_extended = {{20{instruction[31]}}, instruction[31:20]};
                
            7'b0100011: // S-type
                imm_extended = {{20{instruction[31]}}, instruction[31:25], instruction[11:7]};
                
            7'b1100011: // B-type
                imm_extended = {{20{instruction[31]}}, instruction[7], instruction[30:25], instruction[11:8], 1'b0};
                
            7'b0110111, // U-type LUI
            7'b0010111: // U-type AUIPC
                imm_extended = {instruction[31:12], 12'h000};
                
            7'b1101111: // J-type JAL
                imm_extended = {{12{instruction[31]}}, instruction[19:12], instruction[20], instruction[30:21], 1'b0};
                
            default:
                imm_extended = 32'h0;
        endcase
    end

endmodule

register_file.v
module register_file (
    input wire clk,
    input wire rst_n,
    input wire reg_write,
    input wire [4:0] read_reg1,
    input wire [4:0] read_reg2,
    input wire [4:0] write_reg,
    input wire [31:0] write_data,
    output wire [31:0] read_data1,
    output wire [31:0] read_data2
);

    // 32 registers, each 32-bit wide
    reg [31:0] registers [0:31];
    integer i;
    
    // Initialize all registers to 0
    initial begin
        for (i = 0; i < 32; i = i + 1)
            registers[i] = 32'h0;
    end
    
    // Write operation (at positive clock edge)
    always @(posedge clk) begin
        if (reg_write && write_reg != 0) // Register x0 must always be 0
            registers[write_reg] <= write_data;
    end
    
    // Read operations (combinational)
    assign read_data1 = (read_reg1 == 0) ? 32'h0 : registers[read_reg1];
    assign read_data2 = (read_reg2 == 0) ? 32'h0 : registers[read_reg2];

endmodule

control_unit.v
module control_unit (
    input wire [6:0] opcode,
    input wire [2:0] funct3,
    input wire [6:0] funct7,
    output reg reg_write,
    output reg mem_read,
    output reg mem_write,
    output reg branch,
    output reg mem_to_reg,
    output reg alu_src,
    output reg [1:0] alu_op,
    output reg [3:0] alu_control
);

    // RISC-V opcode definitions
    parameter R_TYPE     = 7'b0110011;
    parameter I_TYPE_ALU = 7'b0010011;
    parameter I_TYPE_LOAD = 7'b0000011;
    parameter S_TYPE     = 7'b0100011;
    parameter B_TYPE     = 7'b1100011;
    parameter U_TYPE_LUI = 7'b0110111;
    parameter U_TYPE_AUIPC = 7'b0010111;
    parameter J_TYPE_JAL = 7'b1101111;
    parameter I_TYPE_JALR = 7'b1100111;
    
    // Main control signals
    always @(*) begin
        case(opcode)
            R_TYPE: begin
                reg_write = 1'b1;
                mem_read = 1'b0;
                mem_write = 1'b0;
                branch = 1'b0;
                mem_to_reg = 1'b0;
                alu_src = 1'b0;
                alu_op = 2'b10;
            end
            I_TYPE_ALU: begin
                reg_write = 1'b1;
                mem_read = 1'b0;
                mem_write = 1'b0;
                branch = 1'b0;
                mem_to_reg = 1'b0;
                alu_src = 1'b1;
                alu_op = 2'b10;
            end
            I_TYPE_LOAD: begin
                reg_write = 1'b1;
                mem_read = 1'b1;
                mem_write = 1'b0;
                branch = 1'b0;
                mem_to_reg = 1'b1;
                alu_src = 1'b1;
                alu_op = 2'b00;
            end
            S_TYPE: begin
                reg_write = 1'b0;
                mem_read = 1'b0;
                mem_write = 1'b1;
                branch = 1'b0;
                mem_to_reg = 1'bx; // Don't care
                alu_src = 1'b1;
                alu_op = 2'b00;
            end
            B_TYPE: begin
                reg_write = 1'b0;
                mem_read = 1'b0;
                mem_write = 1'b0;
                branch = 1'b1;
                mem_to_reg = 1'bx; // Don't care
                alu_src = 1'b0;
                alu_op = 2'b01;
            end
            default: begin
                reg_write = 1'b0;
                mem_read = 1'b0;
                mem_write = 1'b0;
                branch = 1'b0;
                mem_to_reg = 1'b0;
                alu_src = 1'b0;
                alu_op = 2'b00;
            end
        endcase
    end

    // ALU control logic
    always @(*) begin
        case(alu_op)
            2'b00: alu_control = 4'b0000; // ADD for loads/stores
            2'b01: alu_control = 4'b0001; // SUB for branches
            2'b10: begin // R-type or I-type ALU
                case(funct3)
                    3'b000: begin
                        // ADD or SUB (for R-type)
                        if (opcode == R_TYPE && funct7 == 7'b0100000)
                            alu_control = 4'b0001; // SUB
                        else
                            alu_control = 4'b0000; // ADD
                    end
                    3'b001: alu_control = 4'b0101; // SLL
                    3'b010: alu_control = 4'b1000; // SLT
                    3'b011: alu_control = 4'b1001; // SLTU
                    3'b100: alu_control = 4'b0100; // XOR
                    3'b101: begin
                        if (funct7 == 7'b0100000)
                            alu_control = 4'b0111; // SRA
                        else
                            alu_control = 4'b0110; // SRL
                    end
                    3'b110: alu_control = 4'b0011; // OR
                    3'b111: alu_control = 4'b0010; // AND
                    default: alu_control = 4'b0000;
                endcase
            end
            default: alu_control = 4'b0000;
        endcase
    end

endmodule

src/memory/instruction_memory.v
module instruction_memory (
    input wire [31:0] pc,
    output wire [31:0] instruction
);

    // For a simple implementation, we'll use a small ROM
    reg [31:0] memory [0:255]; // 256 words of memory
    integer i, file_handle;
    
    // Initialize from file if provided, otherwise use default program
    initial begin
        // Default: Initialize all memory to 0
        for (i = 0; i < 256; i = i + 1)
            memory[i] = 32'h0;
            
        // Try to load the program
        $display("Loading program from test.hex");
        file_handle = $fopen("test.hex", "r");
        if (file_handle == 0) begin
            $display("ERROR: Could not open test.hex");
        end else begin
            $fclose(file_handle);
            $readmemh("test.hex", memory);
            $display("Program loaded successfully");
        end
        
        // Debug: Display the first few instructions
        $display("First 8 instructions:");
        for (i = 0; i < 8; i = i + 1)
            $display("memory[%0d] = 0x%h", i, memory[i]);
    end
    
    // Word-aligned access (address ignores lower 2 bits)
    assign instruction = memory[pc[9:2]]; // PC is byte-addressed, but memory is word-addressed

endmodule

program_counter.v
module program_counter (
    input wire clk,
    input wire rst_n,
    input wire [31:0] pc_next,
    output reg [31:0] pc_current
);

    always @(posedge clk or negedge rst_n) begin
        if (!rst_n)
            pc_current <= 32'h0;
        else
            pc_current <= pc_next;
    end

endmodule

src/core/riscv_cpu.v
module riscv_cpu (
    input wire clk,
    input wire rst_n,
    output wire [31:0] pc_out
);
    // Wires for connecting components
    wire [31:0] pc_current;
    wire [31:0] pc_next;
    wire [31:0] instruction;
    wire [31:0] alu_result;
    wire [31:0] read_data1, read_data2;
    wire [31:0] imm_extended;
    wire [31:0] write_data;
    wire [31:0] read_data_mem;
    wire [4:0] rd, rs1, rs2;
    wire [2:0] funct3;
    wire [6:0] funct7;
    wire [6:0] opcode;
    
    // Control signals
    wire reg_write;
    wire mem_read;
    wire mem_write;
    wire branch;
    wire mem_to_reg;
    wire alu_src;
    wire [1:0] alu_op;
    wire [3:0] alu_control;
    wire zero_flag;
    wire pc_src;
    
    // Program Counter
    program_counter pc (
        .clk(clk),
        .rst_n(rst_n),
        .pc_next(pc_next),
        .pc_current(pc_current)
    );
    
    // Instruction Memory
    instruction_memory imem (
        .pc(pc_current),
        .instruction(instruction)
    );
    
    // Instruction decoding
    assign opcode = instruction[6:0];
    assign rd = instruction[11:7];
    assign funct3 = instruction[14:12];
    assign rs1 = instruction[19:15];
    assign rs2 = instruction[24:20];
    assign funct7 = instruction[31:25];
    
    // Control Unit
    control_unit cu (
        .opcode(opcode),
        .funct3(funct3),
        .funct7(funct7),
        .reg_write(reg_write),
        .mem_read(mem_read),
        .mem_write(mem_write),
        .branch(branch),
        .mem_to_reg(mem_to_reg),
        .alu_src(alu_src),
        .alu_op(alu_op),
        .alu_control(alu_control)
    );
    
    // Register File
    register_file rf (
        .clk(clk),
        .rst_n(rst_n),
        .reg_write(reg_write),
        .read_reg1(rs1),
        .read_reg2(rs2),
        .write_reg(rd),
        .write_data(write_data),
        .read_data1(read_data1),
        .read_data2(read_data2)
    );
    
    // Immediate Generator
    immediate_generator immgen (
        .instruction(instruction),
        .imm_extended(imm_extended)
    );
    
    // ALU source mux
    wire [31:0] alu_input2 = alu_src ? imm_extended : read_data2;
    
    // ALU
    alu main_alu (
        .a(read_data1),
        .b(alu_input2),
        .alu_control(alu_control),
        .result(alu_result),
        .zero(zero_flag)
    );
    
    // Data Memory
    data_memory dmem (
        .clk(clk),
        .mem_read(mem_read),
        .mem_write(mem_write),
        .address(alu_result),
        .write_data(read_data2),
        .read_data(read_data_mem)
    );
    
    // Write back mux
    assign write_data = mem_to_reg ? read_data_mem : alu_result;
    
    // Branch logic
    assign pc_src = branch & zero_flag;
    assign pc_next = pc_src ? (pc_current + imm_extended) : (pc_current + 4);
    
    // Output
    assign pc_out = pc_current;
    
endmodule

src/testbench/tb_riscv_cpu.v
module tb_riscv_cpu;
    reg clk;
    reg rst_n;
    wire [31:0] pc_out;
    integer i;
    
    // Instantiate the RISC-V CPU
    riscv_cpu dut (
        .clk(clk),
        .rst_n(rst_n),
        .pc_out(pc_out)
    );
    
    // Clock generation
    initial begin
        clk = 0;
        forever #5 clk = ~clk;
    end
    
    // Waveform dumping
    initial begin
        $dumpfile("waveform.vcd");
        $dumpvars(0, tb_riscv_cpu);
    end
    
    // Test sequence
    initial begin
        $display("Starting RISC-V CPU test...");
        
        // Reset the CPU
        rst_n = 0;
        #10;
        rst_n = 1;
        
        // Run longer to allow all instructions to execute
        #1500;  // Increased from 1000 to 1500
        
        // Print register file contents at end
        $display("\nFinal Register File Contents:");
        for (i = 0; i < 10; i = i + 1) begin
            $display("x%0d = %0d (0x%h)", i, dut.rf.registers[i], dut.rf.registers[i]);
        end
        
        // Print Fibonacci sequence from memory
        $display("\nFibonacci Sequence in Memory:");
        for (i = 0; i < 8; i = i + 1) begin
            $display("mem[%0d] = %0d (0x%h)", i, dut.dmem.memory[i], dut.dmem.memory[i]);
        end
        
        // End simulation
        $display("\nEnd of test. PC = %h", pc_out);
        $finish;
    end
    
endmodule

build/waveform.vcd
$date
	Mon Apr 14 17:53:36 2025
$end
$version
	Icarus Verilog
$end
$timescale
	1s
$end
$scope module tb_riscv_cpu $end
$var wire 32 ! pc_out [31:0] $end
$var reg 1 " clk $end
$var reg 1 # rst_n $end
$var integer 32 $ i [31:0] $end
$scope module dut $end
$var wire 1 " clk $end
$var wire 32 % pc_out [31:0] $end
$var wire 1 & pc_src $end
$var wire 1 # rst_n $end
$var wire 1 ' zero_flag $end
$var wire 32 ( write_data [31:0] $end
$var wire 5 ) rs2 [4:0] $end
$var wire 5 * rs1 [4:0] $end
$var wire 1 + reg_write $end
$var wire 32 , read_data_mem [31:0] $end
$var wire 32 - read_data2 [31:0] $end
$var wire 32 . read_data1 [31:0] $end
$var wire 5 / rd [4:0] $end
$var wire 32 0 pc_next [31:0] $end
$var wire 32 1 pc_current [31:0] $end
$var wire 7 2 opcode [6:0] $end
$var wire 1 3 mem_write $end
$var wire 1 4 mem_to_reg $end
$var wire 1 5 mem_read $end
$var wire 32 6 instruction [31:0] $end
$var wire 32 7 imm_extended [31:0] $end
$var wire 7 8 funct7 [6:0] $end
$var wire 3 9 funct3 [2:0] $end
$var wire 1 : branch $end
$var wire 1 ; alu_src $end
$var wire 32 < alu_result [31:0] $end
$var wire 2 = alu_op [1:0] $end
$var wire 32 > alu_input2 [31:0] $end
$var wire 4 ? alu_control [3:0] $end
$scope module cu $end
$var wire 3 @ funct3 [2:0] $end
$var wire 7 A funct7 [6:0] $end
$var wire 7 B opcode [6:0] $end
$var parameter 7 C B_TYPE $end
$var parameter 7 D I_TYPE_ALU $end
$var parameter 7 E I_TYPE_JALR $end
$var parameter 7 F I_TYPE_LOAD $end
$var parameter 7 G J_TYPE_JAL $end
$var parameter 7 H R_TYPE $end
$var parameter 7 I S_TYPE $end
$var parameter 7 J U_TYPE_AUIPC $end
$var parameter 7 K U_TYPE_LUI $end
$var reg 4 L alu_control [3:0] $end
$var reg 2 M alu_op [1:0] $end
$var reg 1 ; alu_src $end
$var reg 1 : branch $end
$var reg 1 5 mem_read $end
$var reg 1 4 mem_to_reg $end
$var reg 1 3 mem_write $end
$var reg 1 + reg_write $end
$upscope $end
$scope module dmem $end
$var wire 1 " clk $end
$var wire 1 5 mem_read $end
$var wire 1 3 mem_write $end
$var wire 32 N write_data [31:0] $end
$var wire 32 O read_data [31:0] $end
$var wire 32 P address [31:0] $end
$var integer 32 Q i [31:0] $end
$upscope $end
$scope module imem $end
$var wire 32 R instruction [31:0] $end
$var wire 32 S pc [31:0] $end
$var integer 32 T file_handle [31:0] $end
$var integer 32 U i [31:0] $end
$upscope $end
$scope module immgen $end
$var wire 32 V instruction [31:0] $end
$var wire 7 W opcode [6:0] $end
$var reg 32 X imm_extended [31:0] $end
$upscope $end
$scope module main_alu $end
$var wire 4 Y alu_control [3:0] $end
$var wire 32 Z b [31:0] $end
$var wire 1 ' zero $end
$var wire 32 [ a [31:0] $end
$var parameter 4 \ ALU_ADD $end
$var parameter 4 ] ALU_AND $end
$var parameter 4 ^ ALU_OR $end
$var parameter 4 _ ALU_SLL $end
$var parameter 4 ` ALU_SLT $end
$var parameter 4 a ALU_SLTU $end
$var parameter 4 b ALU_SRA $end
$var parameter 4 c ALU_SRL $end
$var parameter 4 d ALU_SUB $end
$var parameter 4 e ALU_XOR $end
$var reg 32 f result [31:0] $end
$upscope $end
$scope module pc $end
$var wire 1 " clk $end
$var wire 32 g pc_next [31:0] $end
$var wire 1 # rst_n $end
$var reg 32 h pc_current [31:0] $end
$upscope $end
$scope module rf $end
$var wire 1 " clk $end
$var wire 5 i read_reg1 [4:0] $end
$var wire 5 j read_reg2 [4:0] $end
$var wire 1 + reg_write $end
$var wire 1 # rst_n $end
$var wire 32 k write_data [31:0] $end
$var wire 5 l write_reg [4:0] $end
$var wire 32 m read_data2 [31:0] $end
$var wire 32 n read_data1 [31:0] $end
$var integer 32 o i [31:0] $end
$upscope $end
$upscope $end
$upscope $end
$enddefinitions $end
$comment Show the parameter values. $end
$dumpall
b100 e
b1 d
b110 c
b111 b
b1001 a
b1000 `
b101 _
b11 ^
b10 ]
b0 \
b110111 K
b10111 J
b100011 I
b110011 H
b1101111 G
b11 F
b1100111 E
b10011 D
b1100011 C
$end
#0
$dumpvars
b100000 o
b0 n
b0 m
b1 l
b0 k
b0 j
b0 i
b0 h
b100 g
b0 f
b0 [
b0 Z
b0 Y
b0 X
b10011 W
b10010011 V
b1000 U
b10000000000000000000000000000011 T
b0 S
b10010011 R
b100000000 Q
b0 P
b0 O
b0 N
b10 M
b0 L
b10011 B
b0 A
b0 @
b0 ?
b0 >
b10 =
b0 <
1;
0:
b0 9
b0 8
b0 7
b10010011 6
05
04
03
b10011 2
b0 1
b100 0
b1 /
b0 .
b0 -
b0 ,
1+
b0 *
b0 )
b0 (
1'
0&
b0 %
bx $
0#
0"
b0 !
$end
#5
1"
#10
0"
1#
#15
b1 (
b1 k
0'
b1 <
b1 P
b1 f
b1 >
b1 Z
b1 7
b1 X
b1 )
b1 j
b10 /
b10 l
b100000000000100010011 6
b100000000000100010011 R
b100000000000100010011 V
b1000 0
b1000 g
b100 !
b100 %
b100 1
b100 S
b100 h
1"
#20
0"
#25
b0 (
b0 k
1'
b0 <
b0 P
b0 f
b0 >
b0 Z
b0 7
b0 X
b0 )
b0 j
b11 /
b11 l
b110010011 6
b110010011 R
b110010011 V
b1100 0
b1100 g
b1000 !
b1000 %
b1000 1
b1000 S
b1000 h
1"
#30
0"
#35
b0 =
b0 M
x4
13
0+
b100011 W
b1 )
b1 j
b11 *
b11 i
b10 9
b10 @
b0 /
b0 l
b100011 2
b100011 B
b100011010000000100011 6
b100011010000000100011 R
b100011010000000100011 V
b10000 0
b10000 g
b1100 !
b1100 %
b1100 1
b1100 S
b1100 h
1"
#40
0"
#45
b100 (
b100 k
0'
b100 <
b100 P
b100 f
b100 >
b100 Z
b10 =
b10 M
04
03
1+
b100 7
b100 X
b10011 W
b100 )
b100 j
b0 9
b0 @
b11 /
b11 l
b10011 2
b10011 B
b10000011000000110010011 6
b10000011000000110010011 R
b10000011000000110010011 V
b10100 0
b10100 g
b10000 !
b10000 %
b10000 1
b10000 S
b10000 h
1"
#50
0"
#55
b0x00 (
b0x00 k
b0 >
b0 Z
b1 -
b1 N
b1 m
b0 =
b0 M
x4
13
0+
b100 <
b100 P
b100 f
b0 7
b0 X
b100011 W
b10 )
b10 j
b10 9
b10 @
b0 /
b0 l
b100011 2
b100011 B
b100 .
b100 [
b100 n
b1000011010000000100011 6
b1000011010000000100011 R
b1000011010000000100011 V
b11000 0
b11000 g
b10100 !
b10100 %
b10100 1
b10100 S
b10100 h
1"
#60
0"
#65
b1000 <
b1000 P
b1000 f
b1000 (
b1000 k
b100 >
b100 Z
b0 -
b0 N
b0 m
b10 =
b10 M
04
03
1+
b100 7
b100 X
b10011 W
b100 )
b100 j
b0 9
b0 @
b11 /
b11 l
b10011 2
b10011 B
b10000011000000110010011 6
b10000011000000110010011 R
b10000011000000110010011 V
b11100 0
b11100 g
b11000 !
b11000 %
b11000 1
b11000 S
b11000 h
1"
#70
0"
#75
b1 (
b1 k
b1 >
b1 Z
b1 -
b1 N
b1 m
0;
b1 <
b1 P
b1 f
b0 7
b0 X
b110011 W
b10 )
b10 j
b1 *
b1 i
b100 /
b100 l
b110011 2
b110011 B
b0 .
b0 [
b0 n
b1000001000001000110011 6
b1000001000001000110011 R
b1000001000001000110011 V
b100000 0
b100000 g
b11100 !
b11100 %
b11100 1
b11100 S
b11100 h
1"
#80
0"
#85
b1000 <
b1000 P
b1000 f
b0 >
b0 Z
b0x000 (
b0x000 k
b1000 .
b1000 [
b1000 n
b0 =
b0 M
1;
x4
13
0+
b100011 W
b100 )
b100 j
b11 *
b11 i
b10 9
b10 @
b0 /
b0 l
b100011 2
b100011 B
b10000011010000000100011 6
b10000011010000000100011 R
b10000011010000000100011 V
b100100 0
b100100 g
b100000 !
b100000 %
b100000 1
b100000 S
b100000 h
1"
#90
0"
#95
b1100 <
b1100 P
b1100 f
b1100 (
b1100 k
b100 >
b100 Z
b10 =
b10 M
04
03
1+
b100 7
b100 X
b10011 W
b0 9
b0 @
b11 /
b11 l
b10011 2
b10011 B
b10000011000000110010011 6
b10000011000000110010011 R
b10000011000000110010011 V
b101000 0
b101000 g
b100100 !
b100100 %
b100100 1
b100100 S
b100100 h
1"
#100
0"
#105
b1 (
b1 k
b0 >
b0 Z
b0 -
b0 N
b0 m
b1 <
b1 P
b1 f
b0 7
b0 X
b0 )
b0 j
b10 *
b10 i
b1 /
b1 l
b1 .
b1 [
b1 n
b10000000010010011 6
b10000000010010011 R
b10000000010010011 V
b101100 0
b101100 g
b101000 !
b101000 %
b101000 1
b101000 S
b101000 h
1"
#110
0"
#115
b100 *
b100 i
b10 /
b10 l
b100000000100010011 6
b100000000100010011 R
b100000000100010011 V
b110000 0
b110000 g
b101100 !
b101100 %
b101100 1
b101100 S
b101100 h
1"
#120
0"
#125
b10 (
b10 k
b10 <
b10 P
b10 f
b1 >
b1 Z
b1 -
b1 N
b1 m
0;
b110011 W
b10 )
b10 j
b1 *
b1 i
b100 /
b100 l
b110011 2
b110011 B
b1000001000001000110011 6
b1000001000001000110011 R
b1000001000001000110011 V
b110100 0
b110100 g
b110000 !
b110000 %
b110000 1
b110000 S
b110000 h
1"
#130
0"
#135
b1100 <
b1100 P
b1100 f
b0 >
b0 Z
b0xx00 (
b0xx00 k
b10 -
b10 N
b10 m
b1100 .
b1100 [
b1100 n
b0 =
b0 M
1;
x4
13
0+
b100011 W
b100 )
b100 j
b11 *
b11 i
b10 9
b10 @
b0 /
b0 l
b100011 2
b100011 B
b10000011010000000100011 6
b10000011010000000100011 R
b10000011010000000100011 V
b111000 0
b111000 g
b110100 !
b110100 %
b110100 1
b110100 S
b110100 h
1"
#140
0"
#145
b10000 <
b10000 P
b10000 f
b10000 (
b10000 k
b100 >
b100 Z
b10 =
b10 M
04
03
1+
b100 7
b100 X
b10011 W
b0 9
b0 @
b11 /
b11 l
b10011 2
b10011 B
b10000011000000110010011 6
b10000011000000110010011 R
b10000011000000110010011 V
b111100 0
b111100 g
b111000 !
b111000 %
b111000 1
b111000 S
b111000 h
1"
#150
0"
#155
b1 (
b1 k
b0 >
b0 Z
b0 -
b0 N
b0 m
b1 <
b1 P
b1 f
b0 7
b0 X
b0 )
b0 j
b10 *
b10 i
b1 /
b1 l
b1 .
b1 [
b1 n
b10000000010010011 6
b10000000010010011 R
b10000000010010011 V
b1000000 0
b1000000 g
b111100 !
b111100 %
b111100 1
b111100 S
b111100 h
1"
#160
0"
#165
b10 (
b10 k
b10 <
b10 P
b10 f
b10 .
b10 [
b10 n
b100 *
b100 i
b10 /
b10 l
b100000000100010011 6
b100000000100010011 R
b100000000100010011 V
b1000100 0
b1000100 g
b1000000 !
b1000000 %
b1000000 1
b1000000 S
b1000000 h
1"
#170
0"
#175
b11 (
b11 k
b11 <
b11 P
b11 f
b10 >
b10 Z
b10 -
b10 N
b10 m
b1 .
b1 [
b1 n
0;
b110011 W
b10 )
b10 j
b1 *
b1 i
b100 /
b100 l
b110011 2
b110011 B
b1000001000001000110011 6
b1000001000001000110011 R
b1000001000001000110011 V
b1001000 0
b1001000 g
b1000100 !
b1000100 %
b1000100 1
b1000100 S
b1000100 h
1"
#180
0"
#185
b10000 <
b10000 P
b10000 f
b0 >
b0 Z
b0x0000 (
b0x0000 k
b11 -
b11 N
b11 m
b10000 .
b10000 [
b10000 n
b0 =
b0 M
1;
x4
13
0+
b100011 W
b100 )
b100 j
b11 *
b11 i
b10 9
b10 @
b0 /
b0 l
b100011 2
b100011 B
b10000011010000000100011 6
b10000011010000000100011 R
b10000011010000000100011 V
b1001100 0
b1001100 g
b1001000 !
b1001000 %
b1001000 1
b1001000 S
b1001000 h
1"
#190
0"
#195
b10100 <
b10100 P
b10100 f
b10100 (
b10100 k
b100 >
b100 Z
b10 =
b10 M
04
03
1+
b100 7
b100 X
b10011 W
b0 9
b0 @
b11 /
b11 l
b10011 2
b10011 B
b10000011000000110010011 6
b10000011000000110010011 R
b10000011000000110010011 V
b1010000 0
b1010000 g
b1001100 !
b1001100 %
b1001100 1
b1001100 S
b1001100 h
1"
#200
0"
#205
b10 (
b10 k
b0 >
b0 Z
b0 -
b0 N
b0 m
b10 <
b10 P
b10 f
b0 7
b0 X
b0 )
b0 j
b10 *
b10 i
b1 /
b1 l
b10 .
b10 [
b10 n
b10000000010010011 6
b10000000010010011 R
b10000000010010011 V
b1010100 0
b1010100 g
b1010000 !
b1010000 %
b1010000 1
b1010000 S
b1010000 h
1"
#210
0"
#215
b11 (
b11 k
b11 <
b11 P
b11 f
b11 .
b11 [
b11 n
b100 *
b100 i
b10 /
b10 l
b100000000100010011 6
b100000000100010011 R
b100000000100010011 V
b1011000 0
b1011000 g
b1010100 !
b1010100 %
b1010100 1
b1010100 S
b1010100 h
1"
#220
0"
#225
b101 (
b101 k
b101 <
b101 P
b101 f
b11 >
b11 Z
b11 -
b11 N
b11 m
b10 .
b10 [
b10 n
0;
b110011 W
b10 )
b10 j
b1 *
b1 i
b100 /
b100 l
b110011 2
b110011 B
b1000001000001000110011 6
b1000001000001000110011 R
b1000001000001000110011 V
b1011100 0
b1011100 g
b1011000 !
b1011000 %
b1011000 1
b1011000 S
b1011000 h
1"
#230
0"
#235
b10100 <
b10100 P
b10100 f
b0 >
b0 Z
b0x0x00 (
b0x0x00 k
b101 -
b101 N
b101 m
b10100 .
b10100 [
b10100 n
b0 =
b0 M
1;
x4
13
0+
b100011 W
b100 )
b100 j
b11 *
b11 i
b10 9
b10 @
b0 /
b0 l
b100011 2
b100011 B
b10000011010000000100011 6
b10000011010000000100011 R
b10000011010000000100011 V
b1100000 0
b1100000 g
b1011100 !
b1011100 %
b1011100 1
b1011100 S
b1011100 h
1"
#240
0"
#245
b11000 <
b11000 P
b11000 f
b11000 (
b11000 k
b100 >
b100 Z
b10 =
b10 M
04
03
1+
b100 7
b100 X
b10011 W
b0 9
b0 @
b11 /
b11 l
b10011 2
b10011 B
b10000011000000110010011 6
b10000011000000110010011 R
b10000011000000110010011 V
b1100100 0
b1100100 g
b1100000 !
b1100000 %
b1100000 1
b1100000 S
b1100000 h
1"
#250
0"
#255
b11 (
b11 k
b0 >
b0 Z
b0 -
b0 N
b0 m
b11 <
b11 P
b11 f
b0 7
b0 X
b0 )
b0 j
b10 *
b10 i
b1 /
b1 l
b11 .
b11 [
b11 n
b10000000010010011 6
b10000000010010011 R
b10000000010010011 V
b1101000 0
b1101000 g
b1100100 !
b1100100 %
b1100100 1
b1100100 S
b1100100 h
1"
#260
0"
#265
b101 (
b101 k
b101 <
b101 P
b101 f
b101 .
b101 [
b101 n
b100 *
b100 i
b10 /
b10 l
b100000000100010011 6
b100000000100010011 R
b100000000100010011 V
b1101100 0
b1101100 g
b1101000 !
b1101000 %
b1101000 1
b1101000 S
b1101000 h
1"
#270
0"
#275
b1000 (
b1000 k
b1000 <
b1000 P
b1000 f
b101 >
b101 Z
b101 -
b101 N
b101 m
b11 .
b11 [
b11 n
0;
b110011 W
b10 )
b10 j
b1 *
b1 i
b100 /
b100 l
b110011 2
b110011 B
b1000001000001000110011 6
b1000001000001000110011 R
b1000001000001000110011 V
b1110000 0
b1110000 g
b1101100 !
b1101100 %
b1101100 1
b1101100 S
b1101100 h
1"
#280
0"
#285
b11000 <
b11000 P
b11000 f
b0 >
b0 Z
b0xx000 (
b0xx000 k
b1000 -
b1000 N
b1000 m
b11000 .
b11000 [
b11000 n
b0 =
b0 M
1;
x4
13
0+
b100011 W
b100 )
b100 j
b11 *
b11 i
b10 9
b10 @
b0 /
b0 l
b100011 2
b100011 B
b10000011010000000100011 6
b10000011010000000100011 R
b10000011010000000100011 V
b1110100 0
b1110100 g
b1110000 !
b1110000 %
b1110000 1
b1110000 S
b1110000 h
1"
#290
0"
#295
1'
b0 <
b0 P
b0 f
b0 (
b0 k
b0 -
b0 N
b0 m
b0 .
b0 [
b0 n
0;
04
03
b0 W
b0 )
b0 j
b0 *
b0 i
b0 9
b0 @
b0 2
b0 B
b0 6
b0 R
b0 V
b1111000 0
b1111000 g
b1110100 !
b1110100 %
b1110100 1
b1110100 S
b1110100 h
1"
#300
0"
#305
b1111100 0
b1111100 g
b1111000 !
b1111000 %
b1111000 1
b1111000 S
b1111000 h
1"
#310
0"
#315
b10000000 0
b10000000 g
b1111100 !
b1111100 %
b1111100 1
b1111100 S
b1111100 h
1"
#320
0"
#325
b10000100 0
b10000100 g
b10000000 !
b10000000 %
b10000000 1
b10000000 S
b10000000 h
1"
#330
0"
#335
b10001000 0
b10001000 g
b10000100 !
b10000100 %
b10000100 1
b10000100 S
b10000100 h
1"
#340
0"
#345
b10001100 0
b10001100 g
b10001000 !
b10001000 %
b10001000 1
b10001000 S
b10001000 h
1"
#350
0"
#355
b10010000 0
b10010000 g
b10001100 !
b10001100 %
b10001100 1
b10001100 S
b10001100 h
1"
#360
0"
#365
b10010100 0
b10010100 g
b10010000 !
b10010000 %
b10010000 1
b10010000 S
b10010000 h
1"
#370
0"
#375
b10011000 0
b10011000 g
b10010100 !
b10010100 %
b10010100 1
b10010100 S
b10010100 h
1"
#380
0"
#385
b10011100 0
b10011100 g
b10011000 !
b10011000 %
b10011000 1
b10011000 S
b10011000 h
1"
#390
0"
#395
b10100000 0
b10100000 g
b10011100 !
b10011100 %
b10011100 1
b10011100 S
b10011100 h
1"
#400
0"
#405
b10100100 0
b10100100 g
b10100000 !
b10100000 %
b10100000 1
b10100000 S
b10100000 h
1"
#410
0"
#415
b10101000 0
b10101000 g
b10100100 !
b10100100 %
b10100100 1
b10100100 S
b10100100 h
1"
#420
0"
#425
b10101100 0
b10101100 g
b10101000 !
b10101000 %
b10101000 1
b10101000 S
b10101000 h
1"
#430
0"
#435
b10110000 0
b10110000 g
b10101100 !
b10101100 %
b10101100 1
b10101100 S
b10101100 h
1"
#440
0"
#445
b10110100 0
b10110100 g
b10110000 !
b10110000 %
b10110000 1
b10110000 S
b10110000 h
1"
#450
0"
#455
b10111000 0
b10111000 g
b10110100 !
b10110100 %
b10110100 1
b10110100 S
b10110100 h
1"
#460
0"
